omigami/__init__.py
omigami/_version.py
omigami/authentication.py
omigami/cli.py
omigami/config_default.yaml
omigami/endpoint.py
omigami/exceptions.py
omigami/ms2deepscore.py
omigami/omi_settings.py
omigami/plotting.py
omigami/spec2vec.py
omigami_client-0.2.3.dist-info/LICENSE
omigami_client-0.2.3.dist-info/METADATA
omigami_client-0.2.3.dist-info/WHEEL
omigami_client-0.2.3.dist-info/entry_points.txt
omigami_client-0.2.3.dist-info/top_level.txt
omigami_client-0.2.3.dist-info/RECORD
