Metadata-Version: 2.1
Name: omigami-client
Version: 0.2.3
Summary: A package to access Omigami services.
Home-page: https://github.com/omigami/omigami
Author: Data Revenue GmbH
Author-email: carlos@datarevenue.com
License: MIT license
Keywords: omigami
Platform: UNKNOWN
Classifier: Development Status :: 2 - Pre-Alpha
Classifier: Intended Audience :: Developers
Classifier: License :: OSI Approved :: MIT License
Classifier: Natural Language :: English
Classifier: Programming Language :: Python :: 3.6
Classifier: Programming Language :: Python :: 3.7
License-File: LICENSE
Requires-Dist: matchms (==0.8.2)
Requires-Dist: pandas (==1.1.3)
Requires-Dist: requests (==2.24.0)
Requires-Dist: confuse (==1.4.0)
Requires-Dist: matplotlib (==3.4.2)
Requires-Dist: click (==8.0.1)
Requires-Dist: cryptography (==3.4.7)
Provides-Extra: plots
Requires-Dist: rdkit-pypi (==2021.3.4) ; extra == 'plots'
